dbcurses-0.0.1.data/scripts/dbcurses
dbcurses_modules/__init__.py
dbcurses_modules/connector.py
dbcurses_modules/data_window.py
dbcurses_modules/space_tab.py
dbcurses-0.0.1.dist-info/LICENSE
dbcurses-0.0.1.dist-info/METADATA
dbcurses-0.0.1.dist-info/WHEEL
dbcurses-0.0.1.dist-info/top_level.txt
dbcurses-0.0.1.dist-info/RECORD
