Metadata-Version: 2.1
Name: dbcurses
Version: 0.0.1
Summary: Curses-based application for database visualization
Home-page: https://github.com/Lykos94/dbcurses
Author: Lykos94
Author-email: lukaszmoskwa94@gmail.com
License: UNKNOWN
Platform: UNKNOWN
Classifier: Programming Language :: Python :: 3
Classifier: License :: OSI Approved :: GNU General Public License v3 (GPLv3)
Classifier: Operating System :: Unix
Requires-Python: >=3.6
